qdx_py-0.15.0.dist-info/METADATA
qdx_py-0.15.0.dist-info/WHEEL
qdx_py/__init__.py
qdx_py/qdx_py.cpython-312-x86_64-linux-gnu.so
qdx_py-0.15.0.dist-info/RECORD
